lat2db/.DS_Store
lat2db/__init__.py
lat2db/_config.py
lat2db/bl/__init__.py
lat2db/bl/set_machine.py
lat2db/config.cfg
lat2db/controller/__init__.py
lat2db/controller/get_at_ring_output.py
lat2db/controller/get_machine_output.py
lat2db/controller/index_controller.py
lat2db/controller/machine_controller.py
lat2db/db/bessyii_lattice_json.json
lat2db/db/bessyii_tl_lattice_json.json
lat2db/db/mls_lattice_json.json
lat2db/db/mongo_repository.py
lat2db/model/__init__.py
lat2db/model/accelerator.py
lat2db/model/beam_position_monitor.py
lat2db/model/bending.py
lat2db/model/cavity.py
lat2db/model/drift.py
lat2db/model/element.py
lat2db/model/element_properties.py
lat2db/model/energy.py
lat2db/model/geometric_info.py
lat2db/model/machine.py
lat2db/model/magnetic_element.py
lat2db/model/marker.py
lat2db/model/monitor.py
lat2db/model/octupole.py
lat2db/model/physics_info.py
lat2db/model/quadrupole.py
lat2db/model/sequencer.py
lat2db/model/sextupole.py
lat2db/model/steerer.py
lat2db/model/update_machine.py
lat2db/model/version.py
lat2db/templates/__init__.py
lat2db/templates/index.html
lat2db/templates/main.js
lat2db/templates/main.py
lat2db/tools/__init__.py
lat2db/tools/calculation/model/calculation_paramters.py
lat2db/tools/dtclasses.py
lat2db/tools/export_to_json.py
lat2db/tools/factories/__init__.py
lat2db/tools/factories/pyat.py
lat2db/tools/helper_function.py
lat2db/tools/madx/__init__.py
lat2db/tools/madx/madx.lark
lat2db/tools/madx/madx_lark_parser.py
lat2db/tools/madx/parser.py
lat2db/tools/pyat/__init__.py
lat2db/tools/pyat/bessy2_TL_reflat.py
lat2db/tools/pyat/bessy2_export.py
lat2db/tools/pyat/bessy2_export_draft.py
lat2db/tools/pyat/bessy2_parser.py
lat2db/tools/pyat/mls_sr_reflat.py
lat2db/tools/pyat/parsed_machine_api.py
lat2db/tools/thor_scsi/madx.lark.orig
lat2db/tools/thor_scsi/parser.py
lat2db/tools/thor_scsi/thor_scsi.lark
lat2db/tools/thor_scsi/thor_scsi_lark_parser.py
lat2db-0.0.3.dist-info/METADATA
lat2db-0.0.3.dist-info/WHEEL
lat2db-0.0.3.dist-info/licenses/LICENSE
lat2db-0.0.3.dist-info/RECORD
