Metadata-Version: 2.4
Name: lat2db
Version: 0.0.3
Summary: Storing accelerator lattices as json in mongo
License: GPL-3.0
License-File: LICENSE
Author: Waheedullah Sulaiman Khail
Requires-Python: >=3.7
Classifier: Development Status :: 4 - Beta
Classifier: Intended Audience :: Science/Research
Classifier: License :: OSI Approved :: GNU General Public License (GPL)
Classifier: License :: OSI Approved :: GNU General Public License v3 (GPLv3)
Classifier: Programming Language :: Python :: 3
Classifier: Programming Language :: Python :: 3.7
Classifier: Programming Language :: Python :: 3.8
Classifier: Programming Language :: Python :: 3.9
Classifier: Programming Language :: Python :: 3.10
Classifier: Programming Language :: Python :: 3.11
Classifier: Programming Language :: Python :: 3.12
Classifier: Programming Language :: Python :: 3.13
Classifier: Programming Language :: Python :: 3.14
Classifier: Topic :: Scientific/Engineering :: Physics
Requires-Dist: accelerator-toolbox
Requires-Dist: attrs
Requires-Dist: fastapi
Requires-Dist: httpx
Requires-Dist: jsons
Requires-Dist: lark
Requires-Dist: numpy
Requires-Dist: pydantic
Requires-Dist: pymongo
Requires-Dist: pytest
Requires-Dist: uuid
Requires-Dist: uvicorn
Project-URL: Documentation, https://github.com/hz-b/lat2db
Project-URL: Homepage, https://github.com/hz-b/lat2db
Project-URL: Repository, https://github.com/hz-b/lat2db.git
